colordithering
